mobikit_utils/__init__.py
mobikit_utils/__main__.py
mobikit_utils/cli.py
mobikit_utils/constants.py
mobikit_utils/exceptions.py
mobikit_utils/utils.py
mobikit_utils/query_builder/__init__.py
mobikit_utils/query_builder/constants.py
mobikit_utils-0.1.3.dist-info/LICENSE
mobikit_utils-0.1.3.dist-info/METADATA
mobikit_utils-0.1.3.dist-info/WHEEL
mobikit_utils-0.1.3.dist-info/entry_points.txt
mobikit_utils-0.1.3.dist-info/top_level.txt
mobikit_utils-0.1.3.dist-info/RECORD
