Metadata-Version: 2.1
Name: mobikit-utils
Version: 0.1.3
Summary: Mobikit python utilities
Home-page: UNKNOWN
License: UNKNOWN
Platform: UNKNOWN
Classifier: Programming Language :: Python :: 3
Classifier: License :: OSI Approved :: MIT License
Classifier: Operating System :: OS Independent
Requires-Python: >=3.6
